{"nodes":[{"name":"0.s.x.x","group":2},{"name":"1.s.x.x","group":2},{"name":"188.165.x.x","group":2},{"name":"2.s.x.x","group":2},{"name":"2mdn.net","group":2},{"name":"3.s.x.x","group":2},{"name":"3suisses-game.com","group":2},{"name":"4.s.x.x","group":2},{"name":"5.s.x.x","group":2},{"name":"6.s.x.x","group":2},{"name":"7.s.x.x","group":2},{"name":"78.46.x.x","group":2},{"name":"8.s.x.x","group":2},{"name":"9.s.x.x","group":2},{"name":"accuweather.com","group":2},{"name":"adkontekst.pl","group":2},{"name":"adobe.com","group":2},{"name":"adocean.pl","group":1},{"name":"adtaily.com","group":2},{"name":"adtaily.pl","group":2},{"name":"adview.pl","group":2},{"name":"afilo.pl","group":2},{"name":"arbomedia.pl","group":2},{"name":"bbelements.com","group":2},{"name":"businessclick.com","group":2},{"name":"bydgoski.pl","group":2},{"name":"cafenews.pl","group":2},{"name":"ceneo.pl","group":2},{"name":"cloudfront.net","group":2},{"name":"com.pl","group":2},{"name":"darmowe-sondy.pl","group":2},{"name":"doubleclick.net","group":1},{"name":"dziennik.pl","group":2},{"name":"dziennikwschodni.pl","group":2},{"name":"dziennikzachodni.pl","group":2},{"name":"echodnia.eu","group":2},{"name":"emediate.eu","group":1},{"name":"empik.com","group":2},{"name":"facebook.com","group":0},{"name":"facebook.net","group":2},{"name":"fakt.pl","group":2},{"name":"fbcdn.net","group":2},{"name":"feedburner.com","group":2},{"name":"forsal.pl","group":2},{"name":"fotosik.pl","group":2},{"name":"freshoffer.pl","group":2},{"name":"funspot.pl","group":2},{"name":"g-point.biz","group":2},{"name":"gazeta.pl","group":2},{"name":"gazetakrakowska.pl","group":2},{"name":"gazetalubuska.pl","group":2},{"name":"gazetaolsztynska.pl","group":2},{"name":"gazetaprawna.pl","group":2},{"name":"gemius.pl","group":1},{"name":"google-analytics.com","group":2},{"name":"google.com","group":2},{"name":"google.pl","group":2},{"name":"googleadservices.com","group":1},{"name":"googleapis.com","group":2},{"name":"googlesyndication.com","group":2},{"name":"gosc.pl","group":2},{"name":"gp24.pl","group":2},{"name":"gramy.to","group":2},{"name":"gratka.pl","group":2},{"name":"gstatic.com","group":2},{"name":"hitslink.com","group":1},{"name":"hitsprocessor.com","group":1},{"name":"home.pl","group":2},{"name":"idmnet.pl","group":2},{"name":"imwx.com","group":2},{"name":"infor.pl","group":2},{"name":"jquery.com","group":2},{"name":"klubokazji.pl","group":2},{"name":"konta.pl","group":2},{"name":"krakowpost.com","group":2},{"name":"kurierlubelski.pl","group":2},{"name":"literia.pl","group":2},{"name":"mediainter.net","group":2},{"name":"metaffiliation.com","group":2},{"name":"money.pl","group":2},{"name":"money24.pl","group":2},{"name":"multiscreen.tv","group":2},{"name":"muratordom.pl","group":2},{"name":"najszybszy-wygrywa.pl","group":2},{"name":"neo24.pl","group":2},{"name":"netaffiliation.com","group":2},{"name":"newmedialabs.pl","group":2},{"name":"newpolandexpress.pl","group":2},{"name":"novem.pl","group":2},{"name":"nowiny24.pl","group":2},{"name":"nto.pl","group":2},{"name":"nuggad.net","group":1},{"name":"open.pl","group":2},{"name":"pb.pl","group":2},{"name":"playlink.pl","group":2},{"name":"polityka.pl","group":2},{"name":"polskatimes.pl","group":2},{"name":"pomorska.pl","group":2},{"name":"poradnikzdrowie.pl","group":2},{"name":"poranny.pl","group":2},{"name":"presspublica.pl","group":2},{"name":"przegladsportowy.pl","group":2},{"name":"pulspolski.tv","group":2},{"name":"quartic.pl","group":2},{"name":"regiodom.pl","group":2},{"name":"regiomoto.pl","group":2},{"name":"regiopraca.pl","group":2},{"name":"rp.pl","group":2},{"name":"rzeczobiznesie.eu","group":2},{"name":"rzeczpospolita.pl","group":2},{"name":"se.pl","group":2},{"name":"serving-sys.com","group":1},{"name":"simplestorage.pl","group":2},{"name":"smartadserver.com","group":1},{"name":"smartcontext.pl","group":2},{"name":"sports.pl","group":2},{"name":"stat24.com","group":2},{"name":"staticbc.com","group":2},{"name":"sugester.pl","group":2},{"name":"targeo.pl","group":2},{"name":"totalmoney.pl","group":2},{"name":"tradedoubler.com","group":1},{"name":"tynt.com","group":1},{"name":"urzadzamy.pl","group":2},{"name":"videocms.pl","group":2},{"name":"wbj.pl","group":2},{"name":"weather.com","group":2},{"name":"wm.pl","group":2},{"name":"wprost.pl","group":2},{"name":"wspolczesna.pl","group":2},{"name":"wyborcza.pl","group":2},{"name":"youtube.com","group":0},{"name":"ytimg.com","group":2},{"name":"zanox.com","group":1}],"links":[{"source":0,"target":32,"value":7},{"source":1,"target":32,"value":7},{"source":2,"target":2,"value":7},{"source":2,"target":75,"value":7},{"source":3,"target":32,"value":7},{"source":4,"target":29,"value":7},{"source":4,"target":95,"value":7},{"source":5,"target":32,"value":7},{"source":6,"target":133,"value":7},{"source":7,"target":32,"value":7},{"source":8,"target":32,"value":7},{"source":9,"target":32,"value":7},{"source":10,"target":32,"value":7},{"source":11,"target":11,"value":7},{"source":12,"target":32,"value":7},{"source":13,"target":32,"value":7},{"source":14,"target":14,"value":7},{"source":14,"target":51,"value":7},{"source":14,"target":87,"value":7},{"source":15,"target":34,"value":7},{"source":15,"target":49,"value":7},{"source":15,"target":51,"value":7},{"source":15,"target":75,"value":7},{"source":16,"target":110,"value":7},{"source":17,"target":29,"value":4},{"source":17,"target":33,"value":4},{"source":17,"target":34,"value":4},{"source":17,"target":35,"value":4},{"source":17,"target":49,"value":4},{"source":17,"target":50,"value":4},{"source":17,"target":51,"value":4},{"source":17,"target":61,"value":4},{"source":17,"target":75,"value":4},{"source":17,"target":89,"value":4},{"source":17,"target":90,"value":4},{"source":17,"target":93,"value":4},{"source":17,"target":97,"value":4},{"source":17,"target":99,"value":4},{"source":17,"target":107,"value":4},{"source":17,"target":128,"value":4},{"source":17,"target":129,"value":4},{"source":18,"target":18,"value":7},{"source":19,"target":19,"value":7},{"source":20,"target":49,"value":7},{"source":20,"target":130,"value":7},{"source":21,"target":101,"value":7},{"source":21,"target":110,"value":7},{"source":22,"target":29,"value":7},{"source":22,"target":32,"value":7},{"source":22,"target":49,"value":7},{"source":22,"target":95,"value":7},{"source":22,"target":107,"value":7},{"source":23,"target":29,"value":7},{"source":23,"target":32,"value":7},{"source":23,"target":34,"value":7},{"source":23,"target":38,"value":7},{"source":23,"target":51,"value":7},{"source":23,"target":52,"value":7},{"source":23,"target":60,"value":7},{"source":23,"target":93,"value":7},{"source":23,"target":95,"value":7},{"source":23,"target":107,"value":7},{"source":23,"target":110,"value":7},{"source":23,"target":125,"value":7},{"source":23,"target":128,"value":7},{"source":24,"target":40,"value":7},{"source":24,"target":101,"value":7},{"source":25,"target":25,"value":7},{"source":25,"target":75,"value":7},{"source":26,"target":29,"value":7},{"source":26,"target":34,"value":7},{"source":26,"target":49,"value":7},{"source":26,"target":75,"value":7},{"source":26,"target":93,"value":7},{"source":26,"target":107,"value":7},{"source":26,"target":128,"value":7},{"source":27,"target":40,"value":7},{"source":28,"target":29,"value":7},{"source":28,"target":33,"value":7},{"source":28,"target":50,"value":7},{"source":28,"target":61,"value":7},{"source":28,"target":89,"value":7},{"source":28,"target":90,"value":7},{"source":28,"target":97,"value":7},{"source":28,"target":99,"value":7},{"source":28,"target":129,"value":7},{"source":29,"target":29,"value":7},{"source":29,"target":60,"value":7},{"source":29,"target":107,"value":7},{"source":29,"target":110,"value":7},{"source":30,"target":107,"value":7},{"source":31,"target":25,"value":4},{"source":31,"target":29,"value":4},{"source":31,"target":31,"value":4},{"source":31,"target":32,"value":4},{"source":31,"target":34,"value":4},{"source":31,"target":49,"value":4},{"source":31,"target":51,"value":4},{"source":31,"target":75,"value":4},{"source":31,"target":93,"value":4},{"source":31,"target":95,"value":4},{"source":31,"target":107,"value":4},{"source":31,"target":125,"value":4},{"source":31,"target":130,"value":4},{"source":32,"target":32,"value":7},{"source":32,"target":52,"value":7},{"source":32,"target":125,"value":7},{"source":33,"target":33,"value":7},{"source":33,"target":125,"value":7},{"source":34,"target":34,"value":7},{"source":35,"target":35,"value":7},{"source":35,"target":38,"value":7},{"source":36,"target":93,"value":4},{"source":37,"target":32,"value":7},{"source":37,"target":52,"value":7},{"source":38,"target":25,"value":1},{"source":38,"target":29,"value":1},{"source":38,"target":32,"value":1},{"source":38,"target":33,"value":1},{"source":38,"target":34,"value":1},{"source":38,"target":38,"value":1},{"source":38,"target":40,"value":1},{"source":38,"target":49,"value":1},{"source":38,"target":50,"value":1},{"source":38,"target":61,"value":1},{"source":38,"target":75,"value":1},{"source":38,"target":89,"value":1},{"source":38,"target":90,"value":1},{"source":38,"target":95,"value":1},{"source":38,"target":97,"value":1},{"source":38,"target":99,"value":1},{"source":38,"target":101,"value":1},{"source":38,"target":107,"value":1},{"source":38,"target":129,"value":1},{"source":38,"target":130,"value":1},{"source":39,"target":29,"value":7},{"source":39,"target":40,"value":7},{"source":39,"target":107,"value":7},{"source":40,"target":40,"value":7},{"source":40,"target":51,"value":7},{"source":40,"target":93,"value":7},{"source":40,"target":101,"value":7},{"source":41,"target":34,"value":7},{"source":41,"target":38,"value":7},{"source":41,"target":40,"value":7},{"source":41,"target":41,"value":7},{"source":41,"target":49,"value":7},{"source":41,"target":75,"value":7},{"source":41,"target":107,"value":7},{"source":41,"target":110,"value":7},{"source":41,"target":130,"value":7},{"source":42,"target":29,"value":7},{"source":43,"target":52,"value":7},{"source":44,"target":40,"value":7},{"source":44,"target":44,"value":7},{"source":45,"target":51,"value":7},{"source":46,"target":34,"value":7},{"source":46,"target":49,"value":7},{"source":46,"target":75,"value":7},{"source":47,"target":29,"value":7},{"source":47,"target":47,"value":7},{"source":48,"target":34,"value":7},{"source":48,"target":48,"value":7},{"source":48,"target":52,"value":7},{"source":48,"target":130,"value":7},{"source":49,"target":49,"value":7},{"source":49,"target":95,"value":7},{"source":50,"target":50,"value":7},{"source":50,"target":60,"value":7},{"source":51,"target":34,"value":7},{"source":51,"target":51,"value":7},{"source":51,"target":95,"value":7},{"source":52,"target":32,"value":7},{"source":52,"target":52,"value":7},{"source":52,"target":93,"value":7},{"source":52,"target":95,"value":7},{"source":53,"target":25,"value":4},{"source":53,"target":29,"value":4},{"source":53,"target":32,"value":4},{"source":53,"target":33,"value":4},{"source":53,"target":34,"value":4},{"source":53,"target":35,"value":4},{"source":53,"target":40,"value":4},{"source":53,"target":49,"value":4},{"source":53,"target":50,"value":4},{"source":53,"target":51,"value":4},{"source":53,"target":52,"value":4},{"source":53,"target":60,"value":4},{"source":53,"target":61,"value":4},{"source":53,"target":75,"value":4},{"source":53,"target":89,"value":4},{"source":53,"target":90,"value":4},{"source":53,"target":93,"value":4},{"source":53,"target":95,"value":4},{"source":53,"target":97,"value":4},{"source":53,"target":99,"value":4},{"source":53,"target":101,"value":4},{"source":53,"target":107,"value":4},{"source":53,"target":110,"value":4},{"source":53,"target":125,"value":4},{"source":53,"target":128,"value":4},{"source":53,"target":129,"value":4},{"source":53,"target":130,"value":4},{"source":54,"target":25,"value":7},{"source":54,"target":29,"value":7},{"source":54,"target":32,"value":7},{"source":54,"target":33,"value":7},{"source":54,"target":34,"value":7},{"source":54,"target":35,"value":7},{"source":54,"target":40,"value":7},{"source":54,"target":49,"value":7},{"source":54,"target":50,"value":7},{"source":54,"target":51,"value":7},{"source":54,"target":52,"value":7},{"source":54,"target":60,"value":7},{"source":54,"target":61,"value":7},{"source":54,"target":73,"value":7},{"source":54,"target":75,"value":7},{"source":54,"target":87,"value":7},{"source":54,"target":89,"value":7},{"source":54,"target":90,"value":7},{"source":54,"target":93,"value":7},{"source":54,"target":95,"value":7},{"source":54,"target":97,"value":7},{"source":54,"target":99,"value":7},{"source":54,"target":101,"value":7},{"source":54,"target":107,"value":7},{"source":54,"target":110,"value":7},{"source":54,"target":125,"value":7},{"source":54,"target":128,"value":7},{"source":54,"target":129,"value":7},{"source":54,"target":130,"value":7},{"source":55,"target":40,"value":7},{"source":55,"target":52,"value":7},{"source":55,"target":55,"value":7},{"source":55,"target":74,"value":7},{"source":56,"target":101,"value":7},{"source":57,"target":32,"value":4},{"source":57,"target":34,"value":4},{"source":57,"target":49,"value":4},{"source":57,"target":75,"value":4},{"source":57,"target":130,"value":4},{"source":58,"target":29,"value":7},{"source":58,"target":40,"value":7},{"source":58,"target":44,"value":7},{"source":59,"target":29,"value":7},{"source":59,"target":31,"value":7},{"source":59,"target":49,"value":7},{"source":59,"target":51,"value":7},{"source":59,"target":107,"value":7},{"source":59,"target":125,"value":7},{"source":59,"target":130,"value":7},{"source":60,"target":32,"value":7},{"source":60,"target":60,"value":7},{"source":61,"target":61,"value":7},{"source":62,"target":51,"value":7},{"source":63,"target":34,"value":7},{"source":63,"target":49,"value":7},{"source":63,"target":75,"value":7},{"source":64,"target":40,"value":7},{"source":64,"target":52,"value":7},{"source":65,"target":52,"value":4},{"source":66,"target":52,"value":4},{"source":67,"target":29,"value":7},{"source":67,"target":128,"value":7},{"source":68,"target":125,"value":7},{"source":69,"target":126,"value":7},{"source":70,"target":32,"value":7},{"source":70,"target":52,"value":7},{"source":71,"target":107,"value":7},{"source":72,"target":40,"value":7},{"source":72,"target":101,"value":7},{"source":73,"target":73,"value":7},{"source":74,"target":74,"value":7},{"source":75,"target":75,"value":7},{"source":76,"target":40,"value":7},{"source":76,"target":76,"value":7},{"source":77,"target":107,"value":7},{"source":78,"target":60,"value":7},{"source":79,"target":87,"value":7},{"source":80,"target":80,"value":7},{"source":80,"target":128,"value":7},{"source":81,"target":32,"value":7},{"source":81,"target":52,"value":7},{"source":81,"target":81,"value":7},{"source":82,"target":82,"value":7},{"source":82,"target":110,"value":7},{"source":83,"target":34,"value":7},{"source":83,"target":49,"value":7},{"source":84,"target":128,"value":7},{"source":85,"target":60,"value":7},{"source":86,"target":60,"value":7},{"source":86,"target":128,"value":7},{"source":87,"target":87,"value":7},{"source":88,"target":60,"value":7},{"source":89,"target":89,"value":7},{"source":90,"target":90,"value":7},{"source":91,"target":25,"value":4},{"source":91,"target":29,"value":4},{"source":91,"target":51,"value":4},{"source":91,"target":95,"value":4},{"source":91,"target":107,"value":4},{"source":91,"target":110,"value":4},{"source":91,"target":125,"value":4},{"source":92,"target":34,"value":7},{"source":92,"target":49,"value":7},{"source":93,"target":49,"value":7},{"source":93,"target":93,"value":7},{"source":93,"target":107,"value":7},{"source":94,"target":34,"value":7},{"source":94,"target":49,"value":7},{"source":94,"target":75,"value":7},{"source":95,"target":95,"value":7},{"source":96,"target":34,"value":7},{"source":96,"target":49,"value":7},{"source":96,"target":75,"value":7},{"source":96,"target":93,"value":7},{"source":96,"target":95,"value":7},{"source":96,"target":96,"value":7},{"source":97,"target":97,"value":7},{"source":98,"target":98,"value":7},{"source":98,"target":110,"value":7},{"source":99,"target":99,"value":7},{"source":100,"target":29,"value":7},{"source":100,"target":60,"value":7},{"source":100,"target":100,"value":7},{"source":100,"target":107,"value":7},{"source":101,"target":101,"value":7},{"source":102,"target":34,"value":7},{"source":102,"target":49,"value":7},{"source":102,"target":75,"value":7},{"source":102,"target":102,"value":7},{"source":103,"target":34,"value":7},{"source":103,"target":49,"value":7},{"source":103,"target":75,"value":7},{"source":103,"target":93,"value":7},{"source":104,"target":33,"value":7},{"source":104,"target":50,"value":7},{"source":104,"target":90,"value":7},{"source":104,"target":97,"value":7},{"source":105,"target":33,"value":7},{"source":105,"target":50,"value":7},{"source":105,"target":61,"value":7},{"source":105,"target":90,"value":7},{"source":106,"target":33,"value":7},{"source":106,"target":50,"value":7},{"source":106,"target":90,"value":7},{"source":106,"target":129,"value":7},{"source":107,"target":29,"value":7},{"source":107,"target":38,"value":7},{"source":107,"target":107,"value":7},{"source":108,"target":107,"value":7},{"source":109,"target":107,"value":7},{"source":110,"target":38,"value":7},{"source":110,"target":95,"value":7},{"source":110,"target":110,"value":7},{"source":111,"target":51,"value":4},{"source":111,"target":110,"value":4},{"source":112,"target":75,"value":7},{"source":112,"target":112,"value":7},{"source":113,"target":40,"value":4},{"source":113,"target":101,"value":4},{"source":113,"target":113,"value":4},{"source":113,"target":130,"value":4},{"source":114,"target":49,"value":7},{"source":114,"target":93,"value":7},{"source":115,"target":115,"value":7},{"source":116,"target":29,"value":7},{"source":116,"target":93,"value":7},{"source":116,"target":128,"value":7},{"source":117,"target":40,"value":7},{"source":118,"target":29,"value":7},{"source":118,"target":33,"value":7},{"source":118,"target":35,"value":7},{"source":118,"target":50,"value":7},{"source":118,"target":61,"value":7},{"source":118,"target":89,"value":7},{"source":118,"target":90,"value":7},{"source":118,"target":97,"value":7},{"source":118,"target":99,"value":7},{"source":118,"target":129,"value":7},{"source":119,"target":29,"value":7},{"source":120,"target":32,"value":7},{"source":121,"target":34,"value":4},{"source":121,"target":49,"value":4},{"source":122,"target":130,"value":4},{"source":123,"target":110,"value":7},{"source":124,"target":34,"value":7},{"source":124,"target":49,"value":7},{"source":124,"target":75,"value":7},{"source":124,"target":124,"value":7},{"source":125,"target":125,"value":7},{"source":126,"target":29,"value":7},{"source":126,"target":126,"value":7},{"source":127,"target":49,"value":7},{"source":127,"target":51,"value":7},{"source":128,"target":52,"value":7},{"source":128,"target":95,"value":7},{"source":128,"target":128,"value":7},{"source":129,"target":129,"value":7},{"source":130,"target":75,"value":7},{"source":130,"target":130,"value":7},{"source":131,"target":29,"value":1},{"source":131,"target":33,"value":1},{"source":131,"target":50,"value":1},{"source":131,"target":51,"value":1},{"source":131,"target":61,"value":1},{"source":131,"target":89,"value":1},{"source":131,"target":90,"value":1},{"source":131,"target":97,"value":1},{"source":131,"target":99,"value":1},{"source":131,"target":129,"value":1},{"source":132,"target":132,"value":7},{"source":133,"target":110,"value":4},{"source":133,"target":133,"value":4}]}