{"nodes":[{"name":"20minutos.es","group":2},{"name":"20minutos.tv","group":2},{"name":"247realmedia.com","group":1},{"name":"254a.com","group":1},{"name":"2mdn.net","group":2},{"name":"2o7.net","group":1},{"name":"360yield.com","group":2},{"name":"8tv.cat","group":2},{"name":"abc.es","group":2},{"name":"abmr.net","group":1},{"name":"acens.com","group":2},{"name":"ad-serverparc.nl","group":2},{"name":"ad4mat.nl","group":2},{"name":"adadvisor.net","group":1},{"name":"adap.tv","group":1},{"name":"adbrite.com","group":1},{"name":"adcloud.net","group":2},{"name":"addynamo.com","group":2},{"name":"addynamo.net","group":2},{"name":"adigimedia.es","group":2},{"name":"adjug.com","group":1},{"name":"admeld.com","group":1},{"name":"adn.es","group":2},{"name":"adnxs.com","group":1},{"name":"adoftheyear.com","group":2},{"name":"adrcdn.com","group":2},{"name":"adrcntr.com","group":2},{"name":"adsfac.eu","group":1},{"name":"adtech.de","group":1},{"name":"advertserve.com","group":2},{"name":"adxpose.com","group":1},{"name":"affutd.com","group":2},{"name":"afy11.net","group":1},{"name":"aldaniti.net","group":2},{"name":"amazonaws.com","group":2},{"name":"amgdgt.com","group":1},{"name":"antena3.com","group":2},{"name":"antevenio.com","group":2},{"name":"apmebf.com","group":1},{"name":"as.com","group":2},{"name":"aspnetcdn.com","group":2},{"name":"atdmt.com","group":1},{"name":"atemda.com","group":2},{"name":"atresadvertising.com","group":2},{"name":"audienceiq.com","group":1},{"name":"bet-at-home.com","group":2},{"name":"betclick.com","group":2},{"name":"bidsystem.com","group":1},{"name":"bluekai.com","group":1},{"name":"brightcove.com","group":2},{"name":"canarias7.es","group":2},{"name":"cetrk.com","group":1},{"name":"chango.com","group":1},{"name":"chartbeat.com","group":2},{"name":"chartbeat.net","group":2},{"name":"cincodias.com","group":2},{"name":"cloudfront.net","group":2},{"name":"codigobarras.net","group":2},{"name":"codistream.net","group":2},{"name":"comclick.com","group":2},{"name":"comodoca.com","group":2},{"name":"connextra.com","group":1},{"name":"contextweb.com","group":1},{"name":"controlbanesto.com","group":2},{"name":"definde.com","group":2},{"name":"diariocordoba.com","group":2},{"name":"diariodealcala.es","group":2},{"name":"diariodeibiza.es","group":2},{"name":"diariodenavarra.es","group":2},{"name":"diariosur.es","group":2},{"name":"diariovasco.com","group":2},{"name":"digicert.com","group":2},{"name":"disqus.com","group":2},{"name":"diximedia.es","group":2},{"name":"doubleclick.net","group":1},{"name":"doubleverify.com","group":1},{"name":"ds1.nl","group":2},{"name":"easyvols.org","group":2},{"name":"easyvoyage.com","group":2},{"name":"edgesuite.net","group":1},{"name":"el-mundo.net","group":2},{"name":"elcomercio.es","group":2},{"name":"elcomerciodigital.com","group":2},{"name":"elcorreo.com","group":2},{"name":"elcorreodigital.com","group":2},{"name":"elcorreogallego.es","group":2},{"name":"eldiariomontanes.es","group":2},{"name":"eleconomista.es","group":2},{"name":"elmundo.es","group":2},{"name":"elmundodeportivo.es","group":2},{"name":"elpais.com","group":2},{"name":"elperiodico.cat","group":2},{"name":"elperiodico.com","group":2},{"name":"elperiodicodearagon.com","group":2},{"name":"elperiodicoextremadura.com","group":2},{"name":"elperiodicomediterraneo.com","group":2},{"name":"elpunt.net","group":2},{"name":"elpuntavui.cat","group":2},{"name":"eltiempo.es","group":2},{"name":"eltiempo24.es","group":2},{"name":"epi.es","group":2},{"name":"epimg.net","group":2},{"name":"esradio.fm","group":2},{"name":"eurocasino.com","group":2},{"name":"everesttech.net","group":1},{"name":"expansion.com","group":2},{"name":"facebook.com","group":0},{"name":"facebook.net","group":2},{"name":"farodevigo.es","group":2},{"name":"fbcdn.net","group":2},{"name":"feedburner.com","group":2},{"name":"finanzas.com","group":2},{"name":"fotocasa.es","group":2},{"name":"foxnetworks.com","group":2},{"name":"galiciae.com","group":2},{"name":"gara.net","group":2},{"name":"gmads.net","group":1},{"name":"godaddy.com","group":2},{"name":"google-analytics.com","group":2},{"name":"google.com","group":2},{"name":"google.es","group":2},{"name":"googleadservices.com","group":1},{"name":"googleapis.com","group":2},{"name":"googlesyndication.com","group":2},{"name":"googleusercontent.com","group":2},{"name":"greatviews.de","group":2},{"name":"grupozeta.es","group":2},{"name":"gstatic.com","group":2},{"name":"habitatsoft.com","group":2},{"name":"harrenmedianetwork.com","group":2},{"name":"heias.com","group":1},{"name":"hottraffic.nl","group":2},{"name":"hoymujer.com","group":2},{"name":"hwcdn.net","group":2},{"name":"ib-ibi.com","group":1},{"name":"imrworldwide.com","group":1},{"name":"infobolsanet.com","group":2},{"name":"inskinmedia.com","group":2},{"name":"intereconomia.com","group":2},{"name":"interwetten.com","group":2},{"name":"invitemedia.com","group":1},{"name":"itsfogo.com","group":2},{"name":"ixnp.com","group":2},{"name":"jquery.com","group":2},{"name":"kewego.com","group":2},{"name":"klm.com","group":2},{"name":"krxd.net","group":1},{"name":"lacerca.com","group":2},{"name":"laopinion.es","group":2},{"name":"laopinioncoruna.es","group":2},{"name":"laopiniondemalaga.es","group":2},{"name":"laopiniondemurcia.es","group":2},{"name":"laopiniondemurcia.org","group":2},{"name":"laopiniondezamora.es","group":2},{"name":"laprovincia.es","group":2},{"name":"larazon.es","group":2},{"name":"lasprovincias.es","group":2},{"name":"latiendademarca.com","group":2},{"name":"lavanguardia.com","group":2},{"name":"lavanguardia.es","group":2},{"name":"laverdad.es","group":2},{"name":"lavozdeasturias.es","group":2},{"name":"lavozdegalicia.es","group":2},{"name":"libertaddigital.com","group":2},{"name":"ligatus.com","group":2},{"name":"lijit.com","group":1},{"name":"liverail.com","group":1},{"name":"llnwd.net","group":2},{"name":"lne.es","group":2},{"name":"longtailvideo.com","group":2},{"name":"lotopia.com","group":2},{"name":"marca.com","group":2},{"name":"marcamotor.com","group":2},{"name":"marcaplayer.com","group":2},{"name":"mathtag.com","group":1},{"name":"meaningtool.com","group":2},{"name":"media6degrees.com","group":1},{"name":"mediabrandsww.com","group":2},{"name":"mediaplex.com","group":1},{"name":"metanetwork.com","group":2},{"name":"mookie1.com","group":1},{"name":"mozilla.org","group":2},{"name":"msn.com:81","group":2},{"name":"mundodeportivo.com","group":2},{"name":"mytrckr.com","group":2},{"name":"nexac.com","group":1},{"name":"openx.com","group":1},{"name":"openx.net","group":1},{"name":"optimost.com","group":2},{"name":"orbyt.es","group":2},{"name":"p-td.com","group":1},{"name":"parcproductions.com","group":2},{"name":"performgroup.com","group":2},{"name":"planet49.com","group":2},{"name":"prensauniversal.es","group":2},{"name":"prisacom.com","group":2},{"name":"prisadigital.com","group":2},{"name":"publico-estaticos.es","group":2},{"name":"publico.es","group":2},{"name":"pubmatic.com","group":1},{"name":"quantserve.com","group":1},{"name":"que.es","group":2},{"name":"quisma.com","group":1},{"name":"r4.com","group":2},{"name":"redmediterraneo.com","group":2},{"name":"renr.es","group":2},{"name":"revsci.net","group":1},{"name":"richandreach.com","group":2},{"name":"ru4.com","group":1},{"name":"rubiconproject.com","group":1},{"name":"s3c.es","group":2},{"name":"scorecardresearch.com","group":1},{"name":"selfbank.es","group":2},{"name":"serviapuestas.es","group":2},{"name":"serving-sys.com","group":1},{"name":"smartadserver.com","group":1},{"name":"smartec.es","group":2},{"name":"smt-service.info","group":2},{"name":"snap.com","group":2},{"name":"sociomantic.com","group":1},{"name":"solidarioscantabria.com","group":2},{"name":"soydecamargo.es","group":2},{"name":"soydelbesaya.es","group":2},{"name":"soydeliebana.es","group":2},{"name":"soydepielagos.es","group":2},{"name":"sport.es","group":2},{"name":"sportyou.es","group":2},{"name":"statcounter.com","group":2},{"name":"teltuo.com","group":2},{"name":"thawte.com","group":2},{"name":"tiramillas.net","group":2},{"name":"toctoc.cat","group":2},{"name":"tubemogul.com","group":1},{"name":"tui.nl","group":2},{"name":"turn.com","group":1},{"name":"tutiempo.net","group":2},{"name":"twimg.com","group":2},{"name":"twitter.com","group":0},{"name":"veoxa.com","group":2},{"name":"vidayestilo.es","group":2},{"name":"videoplaza.com","group":2},{"name":"videoplaza.tv","group":2},{"name":"visualchart.com","group":2},{"name":"vuelosbaratos.com","group":2},{"name":"w55c.net","group":1},{"name":"weborama.fr","group":1},{"name":"wehkamp.nl","group":0},{"name":"wibiya.com","group":1},{"name":"williamhill.com","group":2},{"name":"wtp101.com","group":1},{"name":"wunderloop.net","group":1},{"name":"xiti.com","group":1},{"name":"yaencontre.com","group":2},{"name":"yahoo.com","group":1},{"name":"yieldads.com","group":2},{"name":"yieldmanaged.com","group":2},{"name":"yieldmanager.com","group":1},{"name":"yieldmanager.net","group":1},{"name":"youtube.com","group":0},{"name":"ytimg.com","group":2},{"name":"z5x.net","group":2},{"name":"zanox-affiliate.de","group":2},{"name":"zanox.com","group":1},{"name":"zetaestaticos.com","group":2}],"links":[{"source":0,"target":0,"value":7},{"source":0,"target":106,"value":7},{"source":0,"target":198,"value":7},{"source":1,"target":0,"value":7},{"source":2,"target":2,"value":4},{"source":2,"target":39,"value":4},{"source":2,"target":55,"value":4},{"source":2,"target":85,"value":4},{"source":2,"target":90,"value":4},{"source":2,"target":162,"value":4},{"source":2,"target":198,"value":4},{"source":3,"target":3,"value":4},{"source":4,"target":0,"value":7},{"source":4,"target":4,"value":7},{"source":4,"target":8,"value":7},{"source":4,"target":21,"value":7},{"source":4,"target":23,"value":7},{"source":4,"target":55,"value":7},{"source":4,"target":65,"value":7},{"source":4,"target":69,"value":7},{"source":4,"target":70,"value":7},{"source":4,"target":74,"value":7},{"source":4,"target":81,"value":7},{"source":4,"target":83,"value":7},{"source":4,"target":86,"value":7},{"source":4,"target":87,"value":7},{"source":4,"target":88,"value":7},{"source":4,"target":92,"value":7},{"source":4,"target":94,"value":7},{"source":4,"target":95,"value":7},{"source":4,"target":106,"value":7},{"source":4,"target":108,"value":7},{"source":4,"target":114,"value":7},{"source":4,"target":138,"value":7},{"source":4,"target":148,"value":7},{"source":4,"target":149,"value":7},{"source":4,"target":151,"value":7},{"source":4,"target":160,"value":7},{"source":4,"target":161,"value":7},{"source":4,"target":162,"value":7},{"source":4,"target":168,"value":7},{"source":4,"target":201,"value":7},{"source":4,"target":225,"value":7},{"source":4,"target":234,"value":7},{"source":4,"target":256,"value":7},{"source":5,"target":39,"value":4},{"source":5,"target":55,"value":4},{"source":5,"target":90,"value":4},{"source":5,"target":158,"value":4},{"source":6,"target":65,"value":7},{"source":6,"target":68,"value":7},{"source":6,"target":92,"value":7},{"source":6,"target":93,"value":7},{"source":6,"target":94,"value":7},{"source":6,"target":95,"value":7},{"source":6,"target":108,"value":7},{"source":6,"target":148,"value":7},{"source":6,"target":149,"value":7},{"source":6,"target":151,"value":7},{"source":6,"target":161,"value":7},{"source":6,"target":168,"value":7},{"source":6,"target":225,"value":7},{"source":6,"target":234,"value":7},{"source":7,"target":158,"value":7},{"source":8,"target":8,"value":7},{"source":9,"target":69,"value":4},{"source":9,"target":70,"value":4},{"source":9,"target":161,"value":4},{"source":10,"target":87,"value":7},{"source":11,"target":11,"value":7},{"source":11,"target":23,"value":7},{"source":12,"target":12,"value":7},{"source":12,"target":21,"value":7},{"source":13,"target":21,"value":4},{"source":13,"target":234,"value":4},{"source":14,"target":234,"value":4},{"source":15,"target":234,"value":4},{"source":16,"target":16,"value":7},{"source":16,"target":114,"value":7},{"source":17,"target":256,"value":7},{"source":18,"target":17,"value":7},{"source":18,"target":256,"value":7},{"source":19,"target":158,"value":7},{"source":19,"target":183,"value":7},{"source":20,"target":234,"value":4},{"source":21,"target":8,"value":4},{"source":21,"target":21,"value":4},{"source":21,"target":50,"value":4},{"source":21,"target":69,"value":4},{"source":21,"target":70,"value":4},{"source":21,"target":81,"value":4},{"source":21,"target":83,"value":4},{"source":21,"target":86,"value":4},{"source":21,"target":160,"value":4},{"source":21,"target":162,"value":4},{"source":21,"target":201,"value":4},{"source":21,"target":234,"value":4},{"source":22,"target":22,"value":7},{"source":23,"target":21,"value":4},{"source":23,"target":23,"value":4},{"source":23,"target":41,"value":4},{"source":23,"target":50,"value":4},{"source":23,"target":65,"value":4},{"source":23,"target":68,"value":4},{"source":23,"target":74,"value":4},{"source":23,"target":92,"value":4},{"source":23,"target":93,"value":4},{"source":23,"target":94,"value":4},{"source":23,"target":95,"value":4},{"source":23,"target":106,"value":4},{"source":23,"target":108,"value":4},{"source":23,"target":148,"value":4},{"source":23,"target":149,"value":4},{"source":23,"target":151,"value":4},{"source":23,"target":161,"value":4},{"source":23,"target":168,"value":4},{"source":23,"target":179,"value":4},{"source":23,"target":225,"value":4},{"source":23,"target":234,"value":4},{"source":23,"target":249,"value":4},{"source":23,"target":256,"value":4},{"source":24,"target":24,"value":7},{"source":25,"target":74,"value":7},{"source":26,"target":74,"value":7},{"source":27,"target":249,"value":4},{"source":28,"target":45,"value":4},{"source":28,"target":95,"value":4},{"source":28,"target":149,"value":4},{"source":28,"target":225,"value":4},{"source":28,"target":256,"value":4},{"source":29,"target":138,"value":7},{"source":30,"target":21,"value":4},{"source":31,"target":248,"value":7},{"source":32,"target":234,"value":4},{"source":33,"target":22,"value":7},{"source":33,"target":33,"value":7},{"source":34,"target":0,"value":7},{"source":34,"target":69,"value":7},{"source":34,"target":70,"value":7},{"source":34,"target":81,"value":7},{"source":34,"target":83,"value":7},{"source":34,"target":86,"value":7},{"source":34,"target":160,"value":7},{"source":35,"target":114,"value":4},{"source":36,"target":36,"value":7},{"source":36,"target":155,"value":7},{"source":37,"target":37,"value":7},{"source":37,"target":163,"value":7},{"source":38,"target":155,"value":4},{"source":38,"target":183,"value":4},{"source":39,"target":39,"value":7},{"source":39,"target":198,"value":7},{"source":40,"target":163,"value":7},{"source":41,"target":21,"value":4},{"source":41,"target":23,"value":4},{"source":41,"target":41,"value":4},{"source":41,"target":55,"value":4},{"source":41,"target":88,"value":4},{"source":41,"target":92,"value":4},{"source":41,"target":95,"value":4},{"source":41,"target":105,"value":4},{"source":41,"target":108,"value":4},{"source":41,"target":158,"value":4},{"source":41,"target":183,"value":4},{"source":41,"target":256,"value":4},{"source":42,"target":39,"value":7},{"source":42,"target":55,"value":7},{"source":42,"target":90,"value":7},{"source":42,"target":234,"value":7},{"source":43,"target":155,"value":7},{"source":44,"target":68,"value":4},{"source":44,"target":234,"value":4},{"source":45,"target":45,"value":7},{"source":45,"target":55,"value":7},{"source":45,"target":225,"value":7},{"source":46,"target":46,"value":7},{"source":46,"target":215,"value":7},{"source":47,"target":21,"value":4},{"source":48,"target":108,"value":4},{"source":48,"target":114,"value":4},{"source":49,"target":49,"value":7},{"source":49,"target":69,"value":7},{"source":49,"target":70,"value":7},{"source":49,"target":81,"value":7},{"source":49,"target":83,"value":7},{"source":49,"target":86,"value":7},{"source":49,"target":158,"value":7},{"source":49,"target":160,"value":7},{"source":49,"target":201,"value":7},{"source":50,"target":50,"value":7},{"source":50,"target":128,"value":7},{"source":51,"target":225,"value":4},{"source":52,"target":23,"value":4},{"source":53,"target":8,"value":7},{"source":54,"target":8,"value":7},{"source":54,"target":161,"value":7},{"source":54,"target":198,"value":7},{"source":55,"target":55,"value":7},{"source":55,"target":198,"value":7},{"source":56,"target":0,"value":7},{"source":56,"target":225,"value":7},{"source":57,"target":22,"value":7},{"source":57,"target":68,"value":7},{"source":57,"target":85,"value":7},{"source":57,"target":162,"value":7},{"source":57,"target":163,"value":7},{"source":58,"target":226,"value":7},{"source":59,"target":21,"value":7},{"source":60,"target":60,"value":7},{"source":61,"target":61,"value":4},{"source":61,"target":171,"value":4},{"source":62,"target":21,"value":4},{"source":62,"target":234,"value":4},{"source":63,"target":63,"value":7},{"source":64,"target":68,"value":7},{"source":65,"target":65,"value":7},{"source":66,"target":66,"value":7},{"source":67,"target":67,"value":7},{"source":67,"target":149,"value":7},{"source":68,"target":68,"value":7},{"source":69,"target":69,"value":7},{"source":69,"target":83,"value":7},{"source":70,"target":70,"value":7},{"source":70,"target":83,"value":7},{"source":71,"target":71,"value":7},{"source":72,"target":8,"value":7},{"source":72,"target":68,"value":7},{"source":72,"target":69,"value":7},{"source":72,"target":70,"value":7},{"source":72,"target":81,"value":7},{"source":72,"target":83,"value":7},{"source":72,"target":86,"value":7},{"source":72,"target":160,"value":7},{"source":73,"target":85,"value":7},{"source":73,"target":114,"value":7},{"source":74,"target":0,"value":4},{"source":74,"target":8,"value":4},{"source":74,"target":21,"value":4},{"source":74,"target":23,"value":4},{"source":74,"target":37,"value":4},{"source":74,"target":50,"value":4},{"source":74,"target":55,"value":4},{"source":74,"target":65,"value":4},{"source":74,"target":68,"value":4},{"source":74,"target":69,"value":4},{"source":74,"target":70,"value":4},{"source":74,"target":74,"value":4},{"source":74,"target":81,"value":4},{"source":74,"target":83,"value":4},{"source":74,"target":85,"value":4},{"source":74,"target":86,"value":4},{"source":74,"target":87,"value":4},{"source":74,"target":88,"value":4},{"source":74,"target":92,"value":4},{"source":74,"target":94,"value":4},{"source":74,"target":95,"value":4},{"source":74,"target":108,"value":4},{"source":74,"target":114,"value":4},{"source":74,"target":138,"value":4},{"source":74,"target":147,"value":4},{"source":74,"target":148,"value":4},{"source":74,"target":149,"value":4},{"source":74,"target":151,"value":4},{"source":74,"target":155,"value":4},{"source":74,"target":160,"value":4},{"source":74,"target":161,"value":4},{"source":74,"target":162,"value":4},{"source":74,"target":163,"value":4},{"source":74,"target":167,"value":4},{"source":74,"target":168,"value":4},{"source":74,"target":171,"value":4},{"source":74,"target":198,"value":4},{"source":74,"target":201,"value":4},{"source":74,"target":225,"value":4},{"source":74,"target":234,"value":4},{"source":74,"target":249,"value":4},{"source":74,"target":256,"value":4},{"source":75,"target":23,"value":4},{"source":76,"target":23,"value":7},{"source":77,"target":78,"value":7},{"source":77,"target":198,"value":7},{"source":78,"target":78,"value":7},{"source":78,"target":198,"value":7},{"source":79,"target":8,"value":4},{"source":79,"target":65,"value":4},{"source":79,"target":68,"value":4},{"source":79,"target":69,"value":4},{"source":79,"target":74,"value":4},{"source":79,"target":83,"value":4},{"source":79,"target":92,"value":4},{"source":79,"target":93,"value":4},{"source":79,"target":94,"value":4},{"source":79,"target":95,"value":4},{"source":79,"target":108,"value":4},{"source":79,"target":148,"value":4},{"source":79,"target":149,"value":4},{"source":79,"target":151,"value":4},{"source":79,"target":160,"value":4},{"source":79,"target":161,"value":4},{"source":79,"target":168,"value":4},{"source":80,"target":80,"value":7},{"source":80,"target":88,"value":7},{"source":80,"target":105,"value":7},{"source":80,"target":171,"value":7},{"source":81,"target":81,"value":7},{"source":82,"target":81,"value":7},{"source":83,"target":83,"value":7},{"source":83,"target":106,"value":7},{"source":84,"target":83,"value":7},{"source":85,"target":85,"value":7},{"source":86,"target":50,"value":7},{"source":86,"target":86,"value":7},{"source":87,"target":87,"value":7},{"source":87,"target":162,"value":7},{"source":87,"target":198,"value":7},{"source":88,"target":80,"value":7},{"source":88,"target":88,"value":7},{"source":88,"target":105,"value":7},{"source":88,"target":149,"value":7},{"source":88,"target":171,"value":7},{"source":89,"target":183,"value":7},{"source":90,"target":90,"value":7},{"source":90,"target":162,"value":7},{"source":91,"target":91,"value":7},{"source":91,"target":92,"value":7},{"source":92,"target":92,"value":7},{"source":93,"target":93,"value":7},{"source":94,"target":94,"value":7},{"source":95,"target":95,"value":7},{"source":96,"target":96,"value":7},{"source":96,"target":97,"value":7},{"source":97,"target":97,"value":7},{"source":98,"target":0,"value":7},{"source":99,"target":92,"value":7},{"source":100,"target":108,"value":7},{"source":100,"target":148,"value":7},{"source":100,"target":149,"value":7},{"source":100,"target":151,"value":7},{"source":100,"target":168,"value":7},{"source":101,"target":90,"value":7},{"source":102,"target":163,"value":7},{"source":103,"target":103,"value":7},{"source":104,"target":151,"value":4},{"source":105,"target":105,"value":7},{"source":106,"target":0,"value":1},{"source":106,"target":22,"value":1},{"source":106,"target":39,"value":1},{"source":106,"target":50,"value":1},{"source":106,"target":66,"value":1},{"source":106,"target":69,"value":1},{"source":106,"target":70,"value":1},{"source":106,"target":81,"value":1},{"source":106,"target":83,"value":1},{"source":106,"target":85,"value":1},{"source":106,"target":86,"value":1},{"source":106,"target":88,"value":1},{"source":106,"target":92,"value":1},{"source":106,"target":93,"value":1},{"source":106,"target":106,"value":1},{"source":106,"target":108,"value":1},{"source":106,"target":138,"value":1},{"source":106,"target":148,"value":1},{"source":106,"target":149,"value":1},{"source":106,"target":151,"value":1},{"source":106,"target":158,"value":1},{"source":106,"target":160,"value":1},{"source":106,"target":162,"value":1},{"source":106,"target":163,"value":1},{"source":106,"target":168,"value":1},{"source":106,"target":171,"value":1},{"source":106,"target":183,"value":1},{"source":106,"target":198,"value":1},{"source":106,"target":201,"value":1},{"source":106,"target":225,"value":1},{"source":107,"target":0,"value":7},{"source":107,"target":70,"value":7},{"source":107,"target":83,"value":7},{"source":107,"target":163,"value":7},{"source":107,"target":201,"value":7},{"source":108,"target":108,"value":7},{"source":109,"target":0,"value":7},{"source":109,"target":92,"value":7},{"source":109,"target":93,"value":7},{"source":109,"target":106,"value":7},{"source":109,"target":109,"value":7},{"source":109,"target":163,"value":7},{"source":109,"target":225,"value":7},{"source":110,"target":81,"value":7},{"source":111,"target":132,"value":7},{"source":112,"target":0,"value":7},{"source":113,"target":92,"value":7},{"source":113,"target":94,"value":7},{"source":113,"target":95,"value":7},{"source":113,"target":108,"value":7},{"source":113,"target":148,"value":7},{"source":113,"target":149,"value":7},{"source":113,"target":151,"value":7},{"source":113,"target":161,"value":7},{"source":113,"target":168,"value":7},{"source":114,"target":68,"value":7},{"source":114,"target":114,"value":7},{"source":114,"target":149,"value":7},{"source":115,"target":115,"value":7},{"source":116,"target":155,"value":4},{"source":117,"target":117,"value":7},{"source":118,"target":0,"value":7},{"source":118,"target":8,"value":7},{"source":118,"target":22,"value":7},{"source":118,"target":50,"value":7},{"source":118,"target":65,"value":7},{"source":118,"target":66,"value":7},{"source":118,"target":68,"value":7},{"source":118,"target":69,"value":7},{"source":118,"target":70,"value":7},{"source":118,"target":81,"value":7},{"source":118,"target":83,"value":7},{"source":118,"target":85,"value":7},{"source":118,"target":86,"value":7},{"source":118,"target":87,"value":7},{"source":118,"target":92,"value":7},{"source":118,"target":93,"value":7},{"source":118,"target":94,"value":7},{"source":118,"target":95,"value":7},{"source":118,"target":97,"value":7},{"source":118,"target":105,"value":7},{"source":118,"target":108,"value":7},{"source":118,"target":114,"value":7},{"source":118,"target":115,"value":7},{"source":118,"target":138,"value":7},{"source":118,"target":147,"value":7},{"source":118,"target":148,"value":7},{"source":118,"target":149,"value":7},{"source":118,"target":151,"value":7},{"source":118,"target":155,"value":7},{"source":118,"target":157,"value":7},{"source":118,"target":158,"value":7},{"source":118,"target":160,"value":7},{"source":118,"target":161,"value":7},{"source":118,"target":162,"value":7},{"source":118,"target":163,"value":7},{"source":118,"target":168,"value":7},{"source":118,"target":170,"value":7},{"source":118,"target":183,"value":7},{"source":118,"target":198,"value":7},{"source":118,"target":201,"value":7},{"source":118,"target":225,"value":7},{"source":118,"target":226,"value":7},{"source":119,"target":50,"value":7},{"source":119,"target":85,"value":7},{"source":119,"target":87,"value":7},{"source":119,"target":119,"value":7},{"source":119,"target":147,"value":7},{"source":119,"target":151,"value":7},{"source":119,"target":155,"value":7},{"source":119,"target":198,"value":7},{"source":119,"target":201,"value":7},{"source":120,"target":85,"value":7},{"source":120,"target":108,"value":7},{"source":120,"target":148,"value":7},{"source":120,"target":149,"value":7},{"source":120,"target":151,"value":7},{"source":120,"target":168,"value":7},{"source":120,"target":198,"value":7},{"source":120,"target":201,"value":7},{"source":121,"target":50,"value":4},{"source":121,"target":114,"value":4},{"source":121,"target":158,"value":4},{"source":121,"target":183,"value":4},{"source":121,"target":198,"value":4},{"source":122,"target":50,"value":7},{"source":122,"target":87,"value":7},{"source":122,"target":152,"value":7},{"source":123,"target":50,"value":7},{"source":123,"target":55,"value":7},{"source":123,"target":68,"value":7},{"source":123,"target":74,"value":7},{"source":123,"target":85,"value":7},{"source":123,"target":94,"value":7},{"source":123,"target":95,"value":7},{"source":123,"target":108,"value":7},{"source":123,"target":114,"value":7},{"source":123,"target":147,"value":7},{"source":123,"target":148,"value":7},{"source":123,"target":151,"value":7},{"source":123,"target":162,"value":7},{"source":123,"target":168,"value":7},{"source":123,"target":198,"value":7},{"source":124,"target":106,"value":7},{"source":124,"target":122,"value":7},{"source":125,"target":158,"value":7},{"source":126,"target":65,"value":7},{"source":126,"target":68,"value":7},{"source":126,"target":92,"value":7},{"source":126,"target":93,"value":7},{"source":126,"target":94,"value":7},{"source":126,"target":95,"value":7},{"source":126,"target":108,"value":7},{"source":126,"target":148,"value":7},{"source":126,"target":149,"value":7},{"source":126,"target":151,"value":7},{"source":126,"target":161,"value":7},{"source":126,"target":168,"value":7},{"source":126,"target":198,"value":7},{"source":126,"target":225,"value":7},{"source":127,"target":85,"value":7},{"source":127,"target":87,"value":7},{"source":127,"target":119,"value":7},{"source":127,"target":151,"value":7},{"source":127,"target":155,"value":7},{"source":127,"target":198,"value":7},{"source":127,"target":201,"value":7},{"source":128,"target":50,"value":7},{"source":128,"target":128,"value":7},{"source":128,"target":162,"value":7},{"source":129,"target":65,"value":7},{"source":129,"target":93,"value":7},{"source":129,"target":148,"value":7},{"source":129,"target":149,"value":7},{"source":129,"target":168,"value":7},{"source":129,"target":256,"value":7},{"source":130,"target":21,"value":4},{"source":131,"target":131,"value":7},{"source":131,"target":256,"value":7},{"source":132,"target":69,"value":7},{"source":132,"target":70,"value":7},{"source":132,"target":81,"value":7},{"source":132,"target":83,"value":7},{"source":133,"target":108,"value":7},{"source":133,"target":133,"value":7},{"source":133,"target":148,"value":7},{"source":133,"target":149,"value":7},{"source":133,"target":168,"value":7},{"source":134,"target":148,"value":4},{"source":135,"target":0,"value":4},{"source":135,"target":8,"value":4},{"source":135,"target":39,"value":4},{"source":135,"target":50,"value":4},{"source":135,"target":55,"value":4},{"source":135,"target":65,"value":4},{"source":135,"target":68,"value":4},{"source":135,"target":69,"value":4},{"source":135,"target":70,"value":4},{"source":135,"target":81,"value":4},{"source":135,"target":83,"value":4},{"source":135,"target":85,"value":4},{"source":135,"target":86,"value":4},{"source":135,"target":87,"value":4},{"source":135,"target":88,"value":4},{"source":135,"target":90,"value":4},{"source":135,"target":92,"value":4},{"source":135,"target":93,"value":4},{"source":135,"target":94,"value":4},{"source":135,"target":95,"value":4},{"source":135,"target":97,"value":4},{"source":135,"target":105,"value":4},{"source":135,"target":108,"value":4},{"source":135,"target":114,"value":4},{"source":135,"target":135,"value":4},{"source":135,"target":138,"value":4},{"source":135,"target":148,"value":4},{"source":135,"target":149,"value":4},{"source":135,"target":151,"value":4},{"source":135,"target":155,"value":4},{"source":135,"target":160,"value":4},{"source":135,"target":161,"value":4},{"source":135,"target":162,"value":4},{"source":135,"target":163,"value":4},{"source":135,"target":168,"value":4},{"source":135,"target":171,"value":4},{"source":135,"target":198,"value":4},{"source":135,"target":201,"value":4},{"source":135,"target":225,"value":4},{"source":136,"target":163,"value":7},{"source":137,"target":137,"value":7},{"source":138,"target":138,"value":7},{"source":139,"target":139,"value":7},{"source":140,"target":21,"value":4},{"source":140,"target":23,"value":4},{"source":141,"target":39,"value":7},{"source":141,"target":141,"value":7},{"source":141,"target":171,"value":7},{"source":142,"target":218,"value":7},{"source":143,"target":92,"value":7},{"source":144,"target":144,"value":7},{"source":144,"target":217,"value":7},{"source":145,"target":145,"value":7},{"source":146,"target":65,"value":4},{"source":146,"target":68,"value":4},{"source":146,"target":92,"value":4},{"source":146,"target":93,"value":4},{"source":146,"target":94,"value":4},{"source":146,"target":95,"value":4},{"source":146,"target":108,"value":4},{"source":146,"target":148,"value":4},{"source":146,"target":149,"value":4},{"source":146,"target":151,"value":4},{"source":146,"target":161,"value":4},{"source":146,"target":168,"value":4},{"source":146,"target":225,"value":4},{"source":147,"target":95,"value":7},{"source":147,"target":147,"value":7},{"source":148,"target":148,"value":7},{"source":148,"target":151,"value":7},{"source":149,"target":149,"value":7},{"source":150,"target":151,"value":7},{"source":151,"target":106,"value":7},{"source":151,"target":151,"value":7},{"source":151,"target":152,"value":7},{"source":152,"target":151,"value":7},{"source":152,"target":152,"value":7},{"source":153,"target":151,"value":7},{"source":154,"target":148,"value":7},{"source":154,"target":154,"value":7},{"source":155,"target":106,"value":7},{"source":155,"target":155,"value":7},{"source":156,"target":160,"value":7},{"source":157,"target":157,"value":7},{"source":157,"target":171,"value":7},{"source":158,"target":158,"value":7},{"source":159,"target":158,"value":7},{"source":159,"target":159,"value":7},{"source":160,"target":160,"value":7},{"source":161,"target":161,"value":7},{"source":162,"target":68,"value":7},{"source":162,"target":128,"value":7},{"source":162,"target":162,"value":7},{"source":163,"target":163,"value":7},{"source":164,"target":74,"value":7},{"source":164,"target":164,"value":7},{"source":164,"target":183,"value":7},{"source":165,"target":234,"value":4},{"source":166,"target":155,"value":4},{"source":166,"target":166,"value":4},{"source":167,"target":39,"value":7},{"source":167,"target":55,"value":7},{"source":167,"target":90,"value":7},{"source":167,"target":158,"value":7},{"source":167,"target":167,"value":7},{"source":168,"target":151,"value":7},{"source":168,"target":168,"value":7},{"source":169,"target":169,"value":7},{"source":170,"target":108,"value":7},{"source":170,"target":148,"value":7},{"source":170,"target":149,"value":7},{"source":170,"target":163,"value":7},{"source":170,"target":170,"value":7},{"source":171,"target":171,"value":7},{"source":172,"target":171,"value":7},{"source":173,"target":171,"value":7},{"source":174,"target":21,"value":4},{"source":174,"target":23,"value":4},{"source":174,"target":168,"value":4},{"source":175,"target":65,"value":7},{"source":175,"target":93,"value":7},{"source":175,"target":148,"value":7},{"source":175,"target":149,"value":7},{"source":175,"target":168,"value":7},{"source":175,"target":256,"value":7},{"source":176,"target":225,"value":4},{"source":177,"target":234,"value":7},{"source":178,"target":23,"value":4},{"source":178,"target":155,"value":4},{"source":178,"target":183,"value":4},{"source":179,"target":21,"value":7},{"source":179,"target":65,"value":7},{"source":179,"target":68,"value":7},{"source":179,"target":74,"value":7},{"source":179,"target":93,"value":7},{"source":179,"target":94,"value":7},{"source":179,"target":95,"value":7},{"source":179,"target":108,"value":7},{"source":179,"target":148,"value":7},{"source":179,"target":149,"value":7},{"source":179,"target":151,"value":7},{"source":179,"target":168,"value":7},{"source":179,"target":179,"value":7},{"source":179,"target":225,"value":7},{"source":180,"target":23,"value":4},{"source":181,"target":181,"value":7},{"source":182,"target":65,"value":7},{"source":183,"target":183,"value":7},{"source":184,"target":21,"value":7},{"source":185,"target":234,"value":4},{"source":186,"target":23,"value":4},{"source":187,"target":21,"value":4},{"source":187,"target":23,"value":4},{"source":187,"target":68,"value":4},{"source":187,"target":234,"value":4},{"source":187,"target":249,"value":4},{"source":188,"target":55,"value":7},{"source":189,"target":105,"value":7},{"source":190,"target":234,"value":4},{"source":191,"target":191,"value":7},{"source":192,"target":106,"value":7},{"source":192,"target":155,"value":7},{"source":192,"target":192,"value":7},{"source":192,"target":198,"value":7},{"source":192,"target":225,"value":7},{"source":193,"target":88,"value":7},{"source":193,"target":138,"value":7},{"source":193,"target":171,"value":7},{"source":193,"target":193,"value":7},{"source":194,"target":66,"value":7},{"source":195,"target":39,"value":7},{"source":195,"target":55,"value":7},{"source":195,"target":90,"value":7},{"source":196,"target":39,"value":7},{"source":197,"target":197,"value":7},{"source":197,"target":198,"value":7},{"source":198,"target":197,"value":7},{"source":198,"target":198,"value":7},{"source":199,"target":23,"value":4},{"source":199,"target":68,"value":4},{"source":199,"target":151,"value":4},{"source":199,"target":234,"value":4},{"source":200,"target":21,"value":4},{"source":200,"target":23,"value":4},{"source":200,"target":65,"value":4},{"source":200,"target":93,"value":4},{"source":200,"target":147,"value":4},{"source":200,"target":148,"value":4},{"source":200,"target":149,"value":4},{"source":200,"target":168,"value":4},{"source":200,"target":247,"value":4},{"source":200,"target":256,"value":4},{"source":201,"target":50,"value":7},{"source":201,"target":201,"value":7},{"source":202,"target":23,"value":4},{"source":202,"target":41,"value":4},{"source":202,"target":106,"value":4},{"source":202,"target":202,"value":4},{"source":202,"target":256,"value":4},{"source":203,"target":203,"value":7},{"source":204,"target":95,"value":7},{"source":204,"target":204,"value":7},{"source":205,"target":108,"value":7},{"source":205,"target":148,"value":7},{"source":205,"target":149,"value":7},{"source":205,"target":151,"value":7},{"source":205,"target":168,"value":7},{"source":206,"target":88,"value":4},{"source":206,"target":105,"value":4},{"source":206,"target":171,"value":4},{"source":207,"target":37,"value":7},{"source":208,"target":68,"value":4},{"source":209,"target":21,"value":4},{"source":209,"target":23,"value":4},{"source":209,"target":92,"value":4},{"source":209,"target":161,"value":4},{"source":209,"target":234,"value":4},{"source":210,"target":87,"value":7},{"source":210,"target":198,"value":7},{"source":210,"target":210,"value":7},{"source":211,"target":0,"value":4},{"source":211,"target":39,"value":4},{"source":211,"target":41,"value":4},{"source":211,"target":55,"value":4},{"source":211,"target":65,"value":4},{"source":211,"target":87,"value":4},{"source":211,"target":88,"value":4},{"source":211,"target":90,"value":4},{"source":211,"target":92,"value":4},{"source":211,"target":93,"value":4},{"source":211,"target":94,"value":4},{"source":211,"target":95,"value":4},{"source":211,"target":105,"value":4},{"source":211,"target":108,"value":4},{"source":211,"target":114,"value":4},{"source":211,"target":148,"value":4},{"source":211,"target":149,"value":4},{"source":211,"target":151,"value":4},{"source":211,"target":158,"value":4},{"source":211,"target":168,"value":4},{"source":211,"target":171,"value":4},{"source":211,"target":183,"value":4},{"source":211,"target":201,"value":4},{"source":211,"target":225,"value":4},{"source":212,"target":158,"value":7},{"source":212,"target":212,"value":7},{"source":213,"target":0,"value":7},{"source":213,"target":213,"value":7},{"source":214,"target":0,"value":4},{"source":214,"target":21,"value":4},{"source":214,"target":23,"value":4},{"source":214,"target":171,"value":4},{"source":214,"target":183,"value":4},{"source":214,"target":198,"value":4},{"source":214,"target":214,"value":4},{"source":215,"target":0,"value":4},{"source":215,"target":22,"value":4},{"source":215,"target":155,"value":4},{"source":215,"target":158,"value":4},{"source":215,"target":162,"value":4},{"source":215,"target":167,"value":4},{"source":215,"target":171,"value":4},{"source":215,"target":183,"value":4},{"source":215,"target":215,"value":4},{"source":216,"target":216,"value":7},{"source":217,"target":114,"value":7},{"source":217,"target":217,"value":7},{"source":218,"target":218,"value":7},{"source":218,"target":256,"value":7},{"source":219,"target":65,"value":4},{"source":219,"target":68,"value":4},{"source":219,"target":92,"value":4},{"source":219,"target":93,"value":4},{"source":219,"target":94,"value":4},{"source":219,"target":95,"value":4},{"source":219,"target":108,"value":4},{"source":219,"target":148,"value":4},{"source":219,"target":149,"value":4},{"source":219,"target":151,"value":4},{"source":219,"target":161,"value":4},{"source":219,"target":168,"value":4},{"source":219,"target":225,"value":4},{"source":220,"target":86,"value":7},{"source":221,"target":86,"value":7},{"source":222,"target":86,"value":7},{"source":223,"target":86,"value":7},{"source":224,"target":86,"value":7},{"source":225,"target":225,"value":7},{"source":226,"target":163,"value":7},{"source":226,"target":226,"value":7},{"source":227,"target":147,"value":7},{"source":228,"target":50,"value":7},{"source":228,"target":228,"value":7},{"source":229,"target":229,"value":7},{"source":230,"target":171,"value":7},{"source":231,"target":91,"value":7},{"source":232,"target":232,"value":4},{"source":233,"target":233,"value":7},{"source":234,"target":21,"value":4},{"source":234,"target":23,"value":4},{"source":234,"target":39,"value":4},{"source":234,"target":68,"value":4},{"source":234,"target":108,"value":4},{"source":234,"target":151,"value":4},{"source":234,"target":234,"value":4},{"source":234,"target":256,"value":4},{"source":235,"target":66,"value":7},{"source":235,"target":235,"value":7},{"source":236,"target":8,"value":7},{"source":236,"target":22,"value":7},{"source":236,"target":66,"value":7},{"source":236,"target":86,"value":7},{"source":236,"target":95,"value":7},{"source":236,"target":138,"value":7},{"source":236,"target":151,"value":7},{"source":236,"target":201,"value":7},{"source":237,"target":8,"value":1},{"source":237,"target":22,"value":1},{"source":237,"target":66,"value":1},{"source":237,"target":86,"value":1},{"source":237,"target":92,"value":1},{"source":237,"target":95,"value":1},{"source":237,"target":138,"value":1},{"source":237,"target":151,"value":1},{"source":237,"target":160,"value":1},{"source":237,"target":201,"value":1},{"source":237,"target":237,"value":1},{"source":238,"target":23,"value":7},{"source":239,"target":108,"value":7},{"source":239,"target":148,"value":7},{"source":239,"target":149,"value":7},{"source":239,"target":151,"value":7},{"source":239,"target":168,"value":7},{"source":240,"target":240,"value":7},{"source":241,"target":241,"value":7},{"source":242,"target":138,"value":7},{"source":242,"target":242,"value":7},{"source":243,"target":108,"value":7},{"source":243,"target":148,"value":7},{"source":243,"target":149,"value":7},{"source":243,"target":151,"value":7},{"source":243,"target":168,"value":7},{"source":244,"target":21,"value":4},{"source":245,"target":8,"value":4},{"source":245,"target":50,"value":4},{"source":245,"target":69,"value":4},{"source":245,"target":70,"value":4},{"source":245,"target":81,"value":4},{"source":245,"target":83,"value":4},{"source":245,"target":86,"value":4},{"source":245,"target":160,"value":4},{"source":245,"target":162,"value":4},{"source":245,"target":201,"value":4},{"source":246,"target":23,"value":1},{"source":247,"target":147,"value":4},{"source":248,"target":171,"value":7},{"source":248,"target":183,"value":7},{"source":248,"target":225,"value":7},{"source":248,"target":248,"value":7},{"source":249,"target":21,"value":4},{"source":249,"target":74,"value":4},{"source":249,"target":92,"value":4},{"source":249,"target":148,"value":4},{"source":249,"target":249,"value":4},{"source":250,"target":92,"value":4},{"source":250,"target":225,"value":4},{"source":251,"target":0,"value":4},{"source":251,"target":85,"value":4},{"source":252,"target":159,"value":7},{"source":252,"target":252,"value":7},{"source":253,"target":74,"value":4},{"source":253,"target":83,"value":4},{"source":253,"target":92,"value":4},{"source":253,"target":93,"value":4},{"source":253,"target":94,"value":4},{"source":253,"target":95,"value":4},{"source":253,"target":149,"value":4},{"source":253,"target":234,"value":4},{"source":253,"target":256,"value":4},{"source":254,"target":256,"value":7},{"source":255,"target":23,"value":7},{"source":256,"target":8,"value":4},{"source":256,"target":21,"value":4},{"source":256,"target":37,"value":4},{"source":256,"target":50,"value":4},{"source":256,"target":65,"value":4},{"source":256,"target":68,"value":4},{"source":256,"target":69,"value":4},{"source":256,"target":74,"value":4},{"source":256,"target":83,"value":4},{"source":256,"target":92,"value":4},{"source":256,"target":93,"value":4},{"source":256,"target":94,"value":4},{"source":256,"target":95,"value":4},{"source":256,"target":108,"value":4},{"source":256,"target":148,"value":4},{"source":256,"target":149,"value":4},{"source":256,"target":151,"value":4},{"source":256,"target":160,"value":4},{"source":256,"target":161,"value":4},{"source":256,"target":168,"value":4},{"source":256,"target":179,"value":4},{"source":256,"target":225,"value":4},{"source":256,"target":256,"value":4},{"source":257,"target":234,"value":4},{"source":257,"target":249,"value":4},{"source":258,"target":66,"value":1},{"source":258,"target":85,"value":1},{"source":258,"target":90,"value":1},{"source":258,"target":161,"value":1},{"source":258,"target":226,"value":1},{"source":258,"target":258,"value":1},{"source":259,"target":258,"value":7},{"source":259,"target":259,"value":7},{"source":260,"target":65,"value":7},{"source":260,"target":68,"value":7},{"source":260,"target":74,"value":7},{"source":260,"target":92,"value":7},{"source":260,"target":93,"value":7},{"source":260,"target":94,"value":7},{"source":260,"target":95,"value":7},{"source":260,"target":106,"value":7},{"source":260,"target":108,"value":7},{"source":260,"target":148,"value":7},{"source":260,"target":149,"value":7},{"source":260,"target":151,"value":7},{"source":260,"target":161,"value":7},{"source":260,"target":168,"value":7},{"source":261,"target":16,"value":7},{"source":261,"target":261,"value":7},{"source":262,"target":16,"value":4},{"source":262,"target":21,"value":4},{"source":262,"target":262,"value":4},{"source":263,"target":65,"value":7},{"source":263,"target":93,"value":7},{"source":263,"target":94,"value":7},{"source":263,"target":95,"value":7},{"source":263,"target":263,"value":7}]}